dsipts/__init__.py
dsipts/version.py
dsipts/data_management/__init__.py
dsipts/data_management/monash.py
dsipts/data_management/public_datasets.py
dsipts/data_structure/__init__.py
dsipts/data_structure/data_structure.py
dsipts/data_structure/modifiers.py
dsipts/data_structure/utils.py
dsipts/models/Autoformer.py
dsipts/models/CrossFormer.py
dsipts/models/D3VAE.py
dsipts/models/Diffusion.py
dsipts/models/DilatedConv.py
dsipts/models/DilatedConvED.py
dsipts/models/Duet.py
dsipts/models/ITransformer.py
dsipts/models/Informer.py
dsipts/models/LinearTS.py
dsipts/models/PatchTST.py
dsipts/models/Persistent.py
dsipts/models/RNN.py
dsipts/models/Samformer.py
dsipts/models/Simple.py
dsipts/models/TFT.py
dsipts/models/TIDE.py
dsipts/models/TTM.py
dsipts/models/TimeKAN.py
dsipts/models/TimeXER.py
dsipts/models/TimesNet.py
dsipts/models/VQVAEA.py
dsipts/models/VVA.py
dsipts/models/__init__.py
dsipts/models/base.py
dsipts/models/base_v2.py
dsipts/models/utils.py
dsipts/models/autoformer/__init__.py
dsipts/models/autoformer/layers.py
dsipts/models/crossformer/__init__.py
dsipts/models/crossformer/attn.py
dsipts/models/crossformer/cross_decoder.py
dsipts/models/crossformer/cross_embed.py
dsipts/models/crossformer/cross_encoder.py
dsipts/models/d3vae/__init__.py
dsipts/models/d3vae/diffusion_process.py
dsipts/models/d3vae/embedding.py
dsipts/models/d3vae/encoder.py
dsipts/models/d3vae/model.py
dsipts/models/d3vae/neural_operations.py
dsipts/models/d3vae/resnet.py
dsipts/models/d3vae/utils.py
dsipts/models/duet/__init__.py
dsipts/models/duet/layers.py
dsipts/models/duet/masked.py
dsipts/models/informer/__init__.py
dsipts/models/informer/attn.py
dsipts/models/informer/decoder.py
dsipts/models/informer/embed.py
dsipts/models/informer/encoder.py
dsipts/models/itransformer/Embed.py
dsipts/models/itransformer/SelfAttention_Family.py
dsipts/models/itransformer/Transformer_EncDec.py
dsipts/models/itransformer/__init__.py
dsipts/models/patchtst/__init__.py
dsipts/models/patchtst/layers.py
dsipts-1.1.19.dist-info/METADATA
dsipts-1.1.19.dist-info/WHEEL
dsipts-1.1.19.dist-info/top_level.txt
dsipts-1.1.19.dist-info/RECORD
