Metadata-Version: 2.4
Name: dsipts
Version: 1.1.19
Summary: Unified library for timeseries modelling
Author-email: Andrea Gobbi <agobbi@fbk.eu>
Project-URL: Homepage, https://github.com/DSIP-FBK/DSIPTS
Project-URL: Docs, https://dsip-fbk.github.io/DSIPTS/
Requires-Python: ==3.11.13
Requires-Dist: aim==3.20.1
Requires-Dist: beautifulsoup4==4.12.0
Requires-Dist: bumpver>=2025.1131
Requires-Dist: einops>=0.8.1
Requires-Dist: html-table-parser-python3==0.3.1
Requires-Dist: html5lib>=1.1
Requires-Dist: hydra-core>=1.3.2
Requires-Dist: hydra-joblib-launcher>=1.2.0
Requires-Dist: hydra-optuna-sweeper>=1.2.0
Requires-Dist: hydra-submitit-launcher>=1.2.0
Requires-Dist: ipykernel>=6.30.1
Requires-Dist: lightning>=2.5.4
Requires-Dist: matplotlib>=3.10.6
Requires-Dist: nbformat>=5.10.4
Requires-Dist: numba>=0.61.2
Requires-Dist: numpy<2.0.0
Requires-Dist: pandas>=2.3.2
Requires-Dist: plotly>=6.3.0
Requires-Dist: scikit-learn>=1.7.1
Requires-Dist: sphinx>=8.2.3
Requires-Dist: sphinx-mdinclude>=0.6.2
Requires-Dist: sphinx-pdj-theme>=0.7.3
Requires-Dist: transformers>=4.56.0
